{"g2015-5-14": "bs2072-2-31", "bs2072-2-31": {"dashi": "Trayodashi", "fest": "", "greg": "g2015-5-14"}, "g2015-5-15": "bs2072-2-1", "bs2072-2-32": {"dashi": "Chaturdashi", "fest": "", "greg": "g2015-5-15"}, "bs2072-2-1": {"dashi": "Dwadashi", "fest": "", "greg": "g2015-5-15"}, "g2015-5-16": "bs2072-2-2", "bs2072-2-2": {"dashi": "Trayodashi", "fest": "", "greg": "g2015-5-16"}, "g2015-5-17": "bs2072-2-3", "bs2072-2-3": {"dashi": "Chaturdashi", "fest": "", "greg": "g2015-5-17"}, "g2015-5-18": "bs2072-2-4", "bs2072-2-4": {"dashi": "Aaunshi", "fest": "", "greg": "g2015-5-18"}, "g2015-5-19": "bs2072-2-5", "bs2072-2-5": {"dashi": "Pratipada", "fest": "", "greg": "g2015-5-19"}, "g2015-5-20": "bs2072-2-6", "bs2072-2-6": {"dashi": "Ditiya", "fest": "", "greg": "g2015-5-20"}, "g2015-5-21": "bs2072-2-7", "bs2072-2-7": {"dashi": "Tritiya", "fest": "", "greg": "g2015-5-21"}, "g2015-5-22": "bs2072-2-8", "bs2072-2-8": {"dashi": "Chaturthi", "fest": "", "greg": "g2015-5-22"}, "g2015-5-23": "bs2072-2-9", "bs2072-2-9": {"dashi": "Panchami", "fest": "", "greg": "g2015-5-23"}, "g2015-5-24": "bs2072-2-10", "bs2072-2-10": {"dashi": "Sasthi", "fest": "", "greg": "g2015-5-24"}, "g2015-5-25": "bs2072-2-11", "bs2072-2-11": {"dashi": "Saptami", "fest": "", "greg": "g2015-5-25"}, "g2015-5-26": "bs2072-2-12", "bs2072-2-12": {"dashi": "Aastami", "fest": "", "greg": "g2015-5-26"}, "g2015-5-27": "bs2072-2-13", "bs2072-2-13": {"dashi": "Nawami", "fest": "", "greg": "g2015-5-27"}, "g2015-5-28": "bs2072-2-14", "bs2072-2-14": {"dashi": "Dashami", "fest": "", "greg": "g2015-5-28"}, "g2015-5-29": "bs2072-2-15", "bs2072-2-15": {"dashi": "Ekadashi", "fest": "Ganatantra Diwas", "greg": "g2015-5-29"}, "g2015-5-30": "bs2072-2-16", "bs2072-2-16": {"dashi": "Dwadashi", "fest": "", "greg": "g2015-5-30"}, "g2015-5-31": "bs2072-2-17", "bs2072-2-17": {"dashi": "Trayodashi", "fest": "", "greg": "g2015-5-31"}, "g2015-5-1": "bs2072-2-18", "bs2072-2-18": {"dashi": "Chaturdashi", "fest": "", "greg": "g2015-5-1"}, "g2015-5-2": "bs2072-2-19", "bs2072-2-19": {"dashi": "Purnima", "fest": "", "greg": "g2015-5-2"}, "g2015-5-3": "bs2072-2-20", "bs2072-2-20": {"dashi": "Pratipada", "fest": "", "greg": "g2015-5-3"}, "g2015-5-4": "bs2072-2-21", "bs2072-2-21": {"dashi": "Ditiya", "fest": "", "greg": "g2015-5-4"}, "g2015-5-5": "bs2072-2-22", "bs2072-2-22": {"dashi": "Tritiya", "fest": "", "greg": "g2015-5-5"}, "g2015-5-6": "bs2072-2-23", "bs2072-2-23": {"dashi": "Chaturthi", "fest": "", "greg": "g2015-5-6"}, "g2015-5-7": "bs2072-2-24", "bs2072-2-24": {"dashi": "Panchami", "fest": "", "greg": "g2015-5-7"}, "g2015-5-8": "bs2072-2-25", "bs2072-2-25": {"dashi": "Sasthi", "fest": "", "greg": "g2015-5-8"}, "g2015-5-9": "bs2072-2-26", "bs2072-2-26": {"dashi": "Saptami", "fest": "", "greg": "g2015-5-9"}, "g2015-5-10": "bs2072-2-27", "bs2072-2-27": {"dashi": "Aastami", "fest": "", "greg": "g2015-5-10"}, "g2015-5-11": "bs2072-2-28", "bs2072-2-28": {"dashi": "Nawami", "fest": "", "greg": "g2015-5-11"}, "g2015-5-12": "bs2072-2-29", "bs2072-2-29": {"dashi": "Ekadashi", "fest": "", "greg": "g2015-5-12"}, "g2015-5-13": "bs2072-2-30", "bs2072-2-30": {"dashi": "Dwadashi", "fest": "", "greg": "g2015-5-13"}}