{"g1958-1-14": "bs2014-10-1", "bs2014-10-1": {"dashi": "", "fest": "", "greg": "g1958-1-14"}, "g1958-1-15": "bs2014-10-2", "bs2014-10-2": {"dashi": "", "fest": "", "greg": "g1958-1-15"}, "g1958-1-16": "bs2014-10-3", "bs2014-10-3": {"dashi": "", "fest": "", "greg": "g1958-1-16"}, "g1958-1-17": "bs2014-10-4", "bs2014-10-4": {"dashi": "", "fest": "", "greg": "g1958-1-17"}, "g1958-1-18": "bs2014-10-5", "bs2014-10-5": {"dashi": "", "fest": "", "greg": "g1958-1-18"}, "g1958-1-19": "bs2014-10-6", "bs2014-10-6": {"dashi": "", "fest": "", "greg": "g1958-1-19"}, "g1958-1-20": "bs2014-10-7", "bs2014-10-7": {"dashi": "", "fest": "", "greg": "g1958-1-20"}, "g1958-1-21": "bs2014-10-8", "bs2014-10-8": {"dashi": "", "fest": "", "greg": "g1958-1-21"}, "g1958-1-22": "bs2014-10-9", "bs2014-10-9": {"dashi": "", "fest": "", "greg": "g1958-1-22"}, "g1958-1-23": "bs2014-10-10", "bs2014-10-10": {"dashi": "", "fest": "", "greg": "g1958-1-23"}, "g1958-1-24": "bs2014-10-11", "bs2014-10-11": {"dashi": "", "fest": "", "greg": "g1958-1-24"}, "g1958-1-25": "bs2014-10-12", "bs2014-10-12": {"dashi": "", "fest": "", "greg": "g1958-1-25"}, "g1958-1-26": "bs2014-10-13", "bs2014-10-13": {"dashi": "", "fest": "", "greg": "g1958-1-26"}, "g1958-1-27": "bs2014-10-14", "bs2014-10-14": {"dashi": "", "fest": "", "greg": "g1958-1-27"}, "g1958-1-28": "bs2014-10-15", "bs2014-10-15": {"dashi": "", "fest": "", "greg": "g1958-1-28"}, "g1958-1-29": "bs2014-10-16", "bs2014-10-16": {"dashi": "", "fest": "", "greg": "g1958-1-29"}, "g1958-1-30": "bs2014-10-17", "bs2014-10-17": {"dashi": "", "fest": "", "greg": "g1958-1-30"}, "g1958-1-31": "bs2014-10-18", "bs2014-10-18": {"dashi": "", "fest": "", "greg": "g1958-1-31"}, "g1958-1-1": "bs2014-10-19", "bs2014-10-19": {"dashi": "", "fest": "", "greg": "g1958-1-1"}, "g1958-1-2": "bs2014-10-20", "bs2014-10-20": {"dashi": "", "fest": "", "greg": "g1958-1-2"}, "g1958-1-3": "bs2014-10-21", "bs2014-10-21": {"dashi": "", "fest": "", "greg": "g1958-1-3"}, "g1958-1-4": "bs2014-10-22", "bs2014-10-22": {"dashi": "", "fest": "", "greg": "g1958-1-4"}, "g1958-1-5": "bs2014-10-23", "bs2014-10-23": {"dashi": "", "fest": "", "greg": "g1958-1-5"}, "g1958-1-6": "bs2014-10-24", "bs2014-10-24": {"dashi": "", "fest": "", "greg": "g1958-1-6"}, "g1958-1-7": "bs2014-10-25", "bs2014-10-25": {"dashi": "", "fest": "", "greg": "g1958-1-7"}, "g1958-1-8": "bs2014-10-26", "bs2014-10-26": {"dashi": "", "fest": "", "greg": "g1958-1-8"}, "g1958-1-9": "bs2014-10-27", "bs2014-10-27": {"dashi": "", "fest": "", "greg": "g1958-1-9"}, "g1958-1-10": "bs2014-10-28", "bs2014-10-28": {"dashi": "", "fest": "", "greg": "g1958-1-10"}, "g1958-1-11": "bs2014-10-29", "bs2014-10-29": {"dashi": "", "fest": "", "greg": "g1958-1-11"}}